README
setup.py
sj2psi/__init__.py
sj2psi.egg-info/PKG-INFO
sj2psi.egg-info/SOURCES.txt
sj2psi.egg-info/dependency_links.txt
sj2psi.egg-info/requires.txt
sj2psi.egg-info/top_level.txt