Metadata-Version: 1.1
Name: sj2psi
Version: 0.1.2
Summary: Convert RNA-STAR SJ.out.tab files to 5-prime and 3-prime "percent spliced in" ("psi") scores.
Home-page: http://olgabot.github.io/prettyplotlib
Author: Olga B. Botvinnik
Author-email: olga.botvinnik@gmail.com
License: MIT License
Platform: UNKNOWN
Classifier: Development Status :: 3 - Alpha
Classifier: Intended Audience :: Science/Research
Classifier: License :: OSI Approved :: MIT License
Classifier: Operating System :: OS Independent
Classifier: Programming Language :: Python :: 2.6
Classifier: Programming Language :: Python :: 2.7
Classifier: Programming Language :: Python :: 3.3
Classifier: Topic :: Scientific/Engineering
